TauCeti/__init__.py
tdpTauCeti/__init__.py
tdpTauCeti/tweenerTest.py
tdpTauCeti/PresetChopMapper/PresetChopMapper.tox
tdpTauCeti/PresetChopMapper/extPresetMapper.py
tdpTauCeti/PresetCuelist/PresetCuelist.tox
tdpTauCeti/PresetCuelist/extCuelist.py
tdpTauCeti/PresetDashboard/PresetDashboard.tox
tdpTauCeti/PresetDashboard/__init__.py
tdpTauCeti/PresetDashboard/extDashboard.py
tdpTauCeti/PresetManager/ParUtils.py
tdpTauCeti/PresetManager/PresetManager.tox
tdpTauCeti/PresetManager/__init__.py
tdpTauCeti/PresetManager/extParStack.py
tdpTauCeti/PresetManager/extTauCetiManager.py
tdpTauCeti/PresetManager/ui/ui.tox
tdpTauCeti/Tweener/Exceptions.py
tdpTauCeti/Tweener/TweenObject.py
tdpTauCeti/Tweener/TweenValue.py
tdpTauCeti/Tweener/Tweener.tox
tdpTauCeti/Tweener/__init__.py
tdpTauCeti/Tweener/extTweener.py
tdpTauCeti/Tweener/curves/curves.tox
tdp_tauceti-5.1.4.dist-info/licenses/LICENSE
tdp_tauceti-5.1.4.dist-info/METADATA
tdp_tauceti-5.1.4.dist-info/WHEEL
tdp_tauceti-5.1.4.dist-info/top_level.txt
tdp_tauceti-5.1.4.dist-info/RECORD
