Metadata-Version: 2.4
Name: tdp-TauCeti
Version: 5.1.4
Summary: Presetmanagement and parameer manipulation in TouchDesigner.
Author-email: Wieland Hilker <wieland@plusplus.one>
Project-URL: Website, https://plusplus.one
Project-URL: Repository, https://github.com/PlusPlusOneGmbH/TD_TauCeti_Presetsystem
Keywords: TouchDesigner,Parameter,Tweener,2023.12000
Requires-Python: >=3.11
License-File: LICENSE
Dynamic: license-file
